visa_instrument_drivers/__init__.py
visa_instrument_drivers/rigol_dp800.py
visa_instrument_drivers/rigol_mso5000.py
visa_instrument_drivers-0.1.0.dist-info/METADATA
visa_instrument_drivers-0.1.0.dist-info/WHEEL
visa_instrument_drivers-0.1.0.dist-info/licenses/LICENSE
visa_instrument_drivers-0.1.0.dist-info/RECORD
