Metadata-Version: 2.4
Name: visa-instrument-drivers
Version: 0.1.0
Summary: Tiny, pragmatic VISA instrument drivers on top of PyVISA.
Project-URL: Homepage, https://github.com/yourname/visa-instrument-drivers
Project-URL: Issues, https://github.com/yourname/visa-instrument-drivers/issues
Author-email: Your Name <you@example.com>
License: MIT
License-File: LICENSE
Keywords: PyVISA,SCPI,VISA,automation,instruments,rigol
Classifier: Intended Audience :: Developers
Classifier: License :: OSI Approved :: MIT License
Classifier: Operating System :: OS Independent
Classifier: Programming Language :: Python :: 3
Classifier: Topic :: Scientific/Engineering
Requires-Python: >=3.8
Requires-Dist: pyvisa>=1.13
Provides-Extra: backends
Requires-Dist: pyvisa-py>=0.7; extra == 'backends'
